xray_vision/__init__.py
xray_vision/_version.py
xray_vision/plotter.py
xray_vision/backend/__init__.py
xray_vision/backend/mpl/__init__.py
xray_vision/backend/mpl/contour.py
xray_vision/backend/mpl/cross_section_2d.py
xray_vision/backend/mpl/stack_1d.py
xray_vision/mask/__init__.py
xray_vision/mask/manual_mask.py
xray_vision/messenger/__init__.py
xray_vision/messenger/_class_factory.py
xray_vision/messenger/mpl/__init__.py
xray_vision/messenger/mpl/cross_section_2d.py
xray_vision/messenger/mpl/stack_1d.py
xray_vision/mpl_plotting/__init__.py
xray_vision/mpl_plotting/misc.py
xray_vision/mpl_plotting/roi.py
xray_vision/mpl_plotting/speckle.py
xray_vision/mpl_plotting/utils.py
xray_vision/qt_widgets/__init__.py
xray_vision/qt_widgets/control_widgets.py
xray_vision/qt_widgets/displaydict.py
xray_vision/qt_widgets/query_widget.py
xray_vision/qt_widgets/real_time.py
xray_vision/qt_widgets/util.py
xray_vision/utils/__init__.py
xray_vision/utils/mpl_helpers.py
xray_vision-0.1.1.dist-info/LICENSE
xray_vision-0.1.1.dist-info/METADATA
xray_vision-0.1.1.dist-info/WHEEL
xray_vision-0.1.1.dist-info/top_level.txt
xray_vision-0.1.1.dist-info/RECORD
