Metadata-Version: 2.1
Name: xray-vision
Version: 0.1.1
Summary: Visualization widgets and plotting helpers targeted at X-Ray Sciences
Home-page: https://github.com/Nikea/xray-vision
Author: Brookhaven National Laboratory
License: UNKNOWN
Platform: UNKNOWN
Requires-Dist: matplotlib
Requires-Dist: numpy
Requires-Dist: pandas
Requires-Dist: pyqt5
Requires-Dist: scipy
Requires-Dist: six
